visual_width/__init__.py
visual_width/visual_width.py
visual_width-0.1.1.dist-info/licenses/LICENSE
visual_width-0.1.1.dist-info/METADATA
visual_width-0.1.1.dist-info/WHEEL
visual_width-0.1.1.dist-info/top_level.txt
visual_width-0.1.1.dist-info/RECORD
