Metadata-Version: 2.4
Name: visual-width
Version: 0.1.1
Summary: A Python library for calculating visual width of text, especially for subtitle display
License: MIT
Project-URL: Homepage, https://github.com/speech2srt/visual-width
Project-URL: Repository, https://github.com/speech2srt/visual-width
Project-URL: Issues, https://github.com/speech2srt/visual-width/issues
Requires-Python: >=3.10
License-File: LICENSE
Dynamic: license-file
